Synx/Synx.py
Synx/__init__.py
Synx/logo.png
Synx/media/vv.png
Synx/media/vv2.png
Synx/media/gen/vv2.png
Synx-0.0.3.dist-info/LICENSE.txt
Synx-0.0.3.dist-info/METADATA
Synx-0.0.3.dist-info/WHEEL
Synx-0.0.3.dist-info/top_level.txt
Synx-0.0.3.dist-info/RECORD
