Metadata-Version: 2.1
Name: Synx
Version: 0.0.3
Summary: A framework for easy and simple creation of user interfaces for Python applications
Home-page: https://eliezerodjao.com/desktop/portfolio.php?sent=synx
Author: Eliezer Odjao
Author-email: eliezerodjaoofficial@gmail.com
License: Proprietary
Project-URL: Source, https://eliezerodjao.com/desktop/portfolio.php?sent=synx
Project-URL: Documentation, https://eliezerodjao.com/docs/Synx0v0v3_User_Documentation.docx
Keywords: GUI graphical user interface UI UX
Platform: UNKNOWN
Classifier: Environment :: Win32 (MS Windows)
Classifier: Environment :: Console
Classifier: Programming Language :: Python
Classifier: Programming Language :: Python :: 3.4
Classifier: License :: Other/Proprietary License
Classifier: Operating System :: Microsoft :: Windows
Classifier: Operating System :: POSIX :: Linux
Classifier: Development Status :: 3 - Alpha
Classifier: Intended Audience :: Developers
Classifier: Intended Audience :: End Users/Desktop
Classifier: Topic :: Software Development :: Libraries :: Application Frameworks
Classifier: Topic :: Software Development :: Libraries :: Python Modules
Requires-Python: ~=3.3
Requires-Dist: Pillow
